ttd_databricks_python/__init__.py
ttd_databricks_python-1.0.2.dist-info/METADATA
ttd_databricks_python-1.0.2.dist-info/WHEEL
ttd_databricks_python-1.0.2.dist-info/top_level.txt
ttd_databricks_python-1.0.2.dist-info/RECORD
