Metadata-Version: 2.4
Name: ttd-databricks-python
Version: 1.0.2
Summary: Client implementation and helper functions for integrating with the TTD Databricks services.
Author: The Trade Desk
License: MIT
Requires-Python: >=3.8
Provides-Extra: dev
Requires-Dist: pytest>=7.0.0; extra == "dev"
Requires-Dist: pytest-cov>=4.0.0; extra == "dev"
